{
  "format": "cluster",
  "dbs": "MAPP",
  "table": "geodata.uk_glx_open_retail_points",
  "qID": "id",
  "geom": "geom_p_4326",
  "srid": "4326",
  "properties": "size_band",
  "cluster_label": "store_name",
  "cluster_cat": "retailer",
  "cluster_kmeans": 0.02,
  "cluster_dbscan": 0.2,
  "markerMin": 6,
  "markerMax": 50,
  "hover": {
    "field": "store_name"
  },
  "dataviews": {
    "Grocery Stores": {
      "display": true,
      "query": "uk_grocery table",
      "selectable": true,
      "viewport": true,
      "table": "geodata.uk_glx_open_retail_points",
      "columns": [
        {
          "field": "store_name",
          "title": "Name"
        },
        {
          "field": "fascia",
          "title": "Fascia"
        },
        {
          "field": "retailer",
          "title": "Retailer"
        },
        {
          "field": "size_sqft",
          "title": "Size (sqft)"
        }
      ]
    }
  },
  "infoj": [
    {
      "type": "key"
    },
    {
      "field": "retailer",
      "title": "Retailer",
      "inline": true
    },
    {
      "field": "fascia",
      "title": "Fascia",
      "inline": true
    },
    {
      "field": "store_name",
      "title": "Name"
    },
    {
      "title": "Address",
      "type": "label"
    },
    {
      "field": "add_one"
    },
    {
      "field": "add_two"
    },
    {
      "field": "locality"
    },
    {
      "field": "postcode"
    },
    {
      "field": "town"
    },
    {
      "field": "size_sqft",
      "title": "Size in sqft",
      "inline": true
    },
    {
      "field": "pqi",
      "title": "PQI"
    }
  ],
  "style": {
    "label": {
      "field": "store_name",
      "declutter": true,
      "strokeColor": "#fff",
      "strokeWidth": 3
    },
    "default": {
      "type": "target",
      "fillColor": "#006666"
    },
    "highlight": {
      "scale": 2.1
    },
    "themes": {
      "Retail - Logos": {
        "type": "categorized",
        "field": "retailer",
        "other": true,
        "cat": {
          "Aldi": {
            "svg": "https://cdn.jsdelivr.net/gh/GEOLYTIX/MapIcons@master/brands/aldi.svg",
            "scale": 2,
            "anchor": [
              0.5,
              0.95
            ]
          },
          "Asda": {
            "svg": "https://cdn.jsdelivr.net/gh/GEOLYTIX/MapIcons@master/brands/asda.svg",
            "scale": 2,
            "anchor": [
              0.5,
              0.95
            ]
          },
          "Booths": {
            "svg": "https://cdn.jsdelivr.net/gh/GEOLYTIX/MapIcons@master/brands/booths.svg",
            "scale": 2,
            "anchor": [
              0.5,
              0.95
            ]
          },
          "Budgens": {
            "svg": "https://cdn.jsdelivr.net/gh/GEOLYTIX/MapIcons@master/brands/budgens.svg",
            "scale": 2,
            "anchor": [
              0.5,
              0.95
            ]
          },
          "Co-op": {
            "svg": "https://cdn.jsdelivr.net/gh/GEOLYTIX/MapIcons@master/brands/coop.svg",
            "scale": 2,
            "anchor": [
              0.5,
              0.95
            ]
          },
          "Iceland": {
            "svg": "https://cdn.jsdelivr.net/gh/GEOLYTIX/MapIcons@master/brands/iceland.svg",
            "scale": 2,
            "anchor": [
              0.5,
              0.95
            ]
          },
          "Lidl": {
            "svg": "https://cdn.jsdelivr.net/gh/GEOLYTIX/MapIcons@master/brands/lidl.svg",
            "scale": 2,
            "anchor": [
              0.5,
              0.95
            ]
          },
          "Morrisons": {
            "svg": "https://cdn.jsdelivr.net/gh/GEOLYTIX/MapIcons@master/brands/morrisons.svg",
            "scale": 2,
            "anchor": [
              0.5,
              0.95
            ]
          },
          "Sainsburys": {
            "label": "Sainsbury's",
            "svg": "https://cdn.jsdelivr.net/gh/GEOLYTIX/MapIcons@master/brands/sainsbury.svg",
            "scale": 2,
            "anchor": [
              0.5,
              0.95
            ]
          },
          "Tesco": {
            "svg": "https://cdn.jsdelivr.net/gh/GEOLYTIX/MapIcons@master/brands/tesco.svg",
            "scale": 2,
            "anchor": [
              0.5,
              0.95
            ]
          },
          "Waitrose": {
            "svg": "https://cdn.jsdelivr.net/gh/GEOLYTIX/MapIcons@master/brands/waitrose.svg",
            "scale": 2,
            "anchor": [
              0.5,
              0.95
            ]
          },
          "Whole Foods Market": {
            "svg": "https://cdn.jsdelivr.net/gh/GEOLYTIX/MapIcons@master/brands/whole_foods.svg",
            "scale": 2,
            "anchor": [
              0.5,
              0.95
            ]
          }
        }
      },
      "Retail - Simple": {
        "type": "categorized",
        "field": "retailer",
        "other": true,
        "cat": {
          "Aldi": {
            "label": "Aldi",
            "style": {
              "fillColor": "#ffbf45",
              "layers": {
                "0.875": "#fa6f08",
                "0.75": "#ef3c11",
                "0.625": "#001f79",
                "0.5": "#02bee3",
                "0.25": "ffffff"
              }
            }
          },
          "Asda": {
            "label": "Asda",
            "style": {
              "fillColor": "#83b923",
              "layers": {
                "0.5": "#ffffff",
                "0.375": "#fdb839"
              }
            }
          },
          "Booths": {
            "label": "Booths",
            "style": {
              "fillColor": "#a12629",
              "layers": {
                "0.5": "#ffffff",
                "0.375": "#a12629"
              }
            }
          },
          "Budgens": {
            "label": "Budgens",
            "style": {
              "fillColor": "#EEEEE0",
              "layers": {
                "0.5": "#679a00",
                "0.375": "#cccb01"
              }
            }
          },
          "Co-op": {
            "label": "The Co-Operative",
            "style": {
              "fillColor": "#0b1e60",
              "layers": {
                "0.625": "#ffffff",
                "0.5": "#a3d227"
              }
            }
          },
          "Costco": {
            "label": "Costco",
            "style": {
              "fillColor": "#005daa",
              "layers": {
                "0.875": "#ffffff",
                "0.625": "#e31837"
              }
            }
          },
          "Farmfoods": {
            "label": "Farm Foods",
            "style": {
              "fillColor": "#77a632",
              "layers": {
                "0.75": "#f7f900",
                "0.5": "#ff0000"
              }
            }
          },
          "Heron": {
            "label": "Heron",
            "style": {
              "fillColor": "#ffffff",
              "layers": {
                "0.75": "#313590",
                "0.25": "#ffcf00"
              }
            }
          },
          "Iceland": {
            "label": "Iceland",
            "style": {
              "fillColor": "#ed1b2d",
              "layers": {
                "0.75": "#f2552b",
                "0.5": "#f89128",
                "0.25": "#ffffff"
              }
            }
          },
          "Lidl": {
            "label": "Lidl",
            "style": {
              "fillColor": "#d61408",
              "layers": {
                "0.875": "#ffe502",
                "0.5": "#002d7a",
                "0.25": "#d61408"
              }
            }
          },
          "Makro": {
            "label": "Makro",
            "style": {
              "fillColor": "#00457a",
              "layers": {
                "0.325": "#ffe811"
              }
            }
          },
          "Marks and Spencer": {
            "label": "Marks & Spencer",
            "style": {
              "fillColor": "#0a0d10",
              "layers": {
                "0.5": "#def036",
                "0.25": "#0a0d10"
              }
            }
          },
          "Morrisons": {
            "label": "Morrisons",
            "style": {
              "fillColor": "#ffe133",
              "layers": {
                "0.5": "#00614e"
              }
            }
          },
          "Sainsburys": {
            "label": "Sainsbury's",
            "style": {
              "fillColor": "#ee8a00",
              "layers": {
                "0.625": "#ffffff",
                "0.325": "#ee8a00"
              }
            }
          },
          "Tesco": {
            "label": "Tesco",
            "style": {
              "fillColor": "#0055a8",
              "layers": {
                "0.75": "#ffffff",
                "0.325": "#f02f26"
              }
            }
          },
          "Waitrose": {
            "label": "Waitrose",
            "style": {
              "fillColor": "#81ae37",
              "layers": {
                "0.325": "#ffffff"
              }
            }
          },
          "Whole Foods Market": {
            "label": "Whole Foods Market",
            "style": {
              "fillColor": "#00674b",
              "layers": {
                "0.875": "#ffffff",
                "0.5": "#00674b"
              }
            }
          }
        }
      }
    }
  }
}
